marshmallow_dynamodb/__init__.py
marshmallow_dynamodb/fields.py
marshmallow_dynamodb-0.0.9.dist-info/LICENSE
marshmallow_dynamodb-0.0.9.dist-info/METADATA
marshmallow_dynamodb-0.0.9.dist-info/WHEEL
marshmallow_dynamodb-0.0.9.dist-info/top_level.txt
marshmallow_dynamodb-0.0.9.dist-info/RECORD
