Metadata-Version: 2.1
Name: marshmallow-dynamodb
Version: 0.0.9
Summary: Extra fields to integrate Marshmallow and DynamoDb
Home-page: https://github.com/truckpad/marshmallow-dynamodb
Author: Leonardo Santos Monteiro
Author-email: leonardo.monteiro@truckpad.com.br
License: UNKNOWN
Platform: UNKNOWN
Classifier: Development Status :: 3 - Alpha
Classifier: Intended Audience :: Developers
Classifier: License :: OSI Approved :: MIT License
Classifier: Programming Language :: Python :: 3
Classifier: Programming Language :: Python :: 3.5
Classifier: Programming Language :: Python :: 3.6
Classifier: Programming Language :: Python :: 3.7
Requires-Dist: marshmallow
